roejobs/__init__.py
roejobs/cli.py
roejobs/jobs.py
roejobs/server.py
roejobs/tui.py
roejobs/utils.py
roejobs/templates/job_detail.html
roejobs/templates/jobs.html
roejobs/templates/log_view.html
roejobs-2026.1.21.post1.dist-info/licenses/LICENSE
roejobs-2026.1.21.post1.dist-info/METADATA
roejobs-2026.1.21.post1.dist-info/WHEEL
roejobs-2026.1.21.post1.dist-info/entry_points.txt
roejobs-2026.1.21.post1.dist-info/top_level.txt
roejobs-2026.1.21.post1.dist-info/RECORD
