Metadata-Version: 2.4
Name: roejobs
Version: 2026.1.21.post1
Summary: Lightweight job runner and supervisor for long-running tasks
Author-email: Adrian Röfer <aroefer@uni-bremen.de>
License: GPLv3
Requires-Python: >=3.9
License-File: LICENSE
Requires-Dist: jinja2
Requires-Dist: textual
Requires-Dist: requests
Provides-Extra: dev
Requires-Dist: pytest; extra == "dev"
Dynamic: license-file
